sssm_core/__init__.py
sssm_core/model.py
sssm_core/saved_models/__init__.py
wrap_sssm/__init__.py
wrap_sssm/detection/__init__.py
wrap_sssm/detection/detection.py
wrap_sssm/utils/__init__.py
wrap_sssm/utils/io.py
sssm-0.0.6.dist-info/METADATA
sssm-0.0.6.dist-info/WHEEL
sssm-0.0.6.dist-info/top_level.txt
sssm-0.0.6.dist-info/RECORD
