Metadata-Version: 2.1
Name: sssm
Version: 0.0.6
Summary: a wrapper of sssm
Author: chendi
Author-email: 3517725675@qq.com
Requires-Dist: requests
Requires-Dist: importlib-metadata
Requires-Dist: torch
Requires-Dist: pandas
Requires-Dist: einops
Requires-Dist: seaborn
Requires-Dist: numpy
Requires-Dist: scipy
Requires-Dist: matplotlib
Requires-Dist: ipywidgets
Requires-Dist: mne
